setup.py
cgi/__init__.py
cgi.unescape.egg-info/PKG-INFO
cgi.unescape.egg-info/SOURCES.txt
cgi.unescape.egg-info/dependency_links.txt
cgi.unescape.egg-info/namespace_packages.txt
cgi.unescape.egg-info/top_level.txt
cgi.unescape.egg-info/zip-safe